keyrings_artifacts/__init__.py
keyrings_artifacts/_version.py
keyrings_artifacts/artifacts.py
keyrings_artifacts/crypt_file.py
keyrings_artifacts/logging_config.py
keyrings_artifacts/provider.py
keyrings_artifacts/support.py
keyrings_artifacts-1.0.2.dist-info/METADATA
keyrings_artifacts-1.0.2.dist-info/WHEEL
keyrings_artifacts-1.0.2.dist-info/entry_points.txt
keyrings_artifacts-1.0.2.dist-info/licenses/LICENSE
keyrings_artifacts-1.0.2.dist-info/RECORD
