Metadata-Version: 2.4
Name: keyrings.artifacts
Version: 1.0.2
Summary: Keyring backend, that automatically retrieves credentials for Azure Artifacts.
Author-email: Jens Lorrmann <jslorrma@gmail.com>
Maintainer-email: Jens Lorrmann <jslorrma@gmail.com>
License-File: LICENSE
Classifier: Development Status :: 5 - Production/Stable
Classifier: Intended Audience :: Developers
Classifier: License :: OSI Approved :: MIT License
Classifier: Programming Language :: Python :: 3
Classifier: Programming Language :: Python :: 3 :: Only
Requires-Python: >=3.7
Requires-Dist: azure-identity>=1.17.1
Requires-Dist: keyring>=16.0
Requires-Dist: keyrings-alt>=5.0.0
Requires-Dist: pycryptodomex>=3.20.0
Requires-Dist: requests>=2.20.0
Requires-Dist: setuptools<76,>=70.0.0
